MANIFEST.in
README.md
setup.cfg
setup.py
chs/VERSION
chs/__init__.py
chs/__main__.py
chs.egg-info/PKG-INFO
chs.egg-info/SOURCES.txt
chs.egg-info/dependency_links.txt
chs.egg-info/entry_points.txt
chs.egg-info/requires.txt
chs.egg-info/top_level.txt
chs/client/__init__.py
chs/client/ending.py
chs/client/runner.py
chs/engine/__init__.py
chs/engine/parser.py
chs/engine/stockfish.py
chs/engine/stockfish_10_x64_linux
chs/engine/stockfish_10_x64_mac
chs/engine/stockfish_10_x64_windows.exe
chs/engine/stockfish_13_x64_mac
chs/ui/__init__.py
chs/ui/board.py
chs/utils/__init__.py
chs/utils/core.py
tests/__init__.py
tests/test_setup.py
tests/framework/__init__.py
tests/framework/base_command_test_case.py