Metadata-Version: 1.1
Name: chs
Version: 3.0.0
Summary: Play chess against the Stockfish engine in your terminal.
Home-page: https://github.com/nickzuber/chs
Author: Nick Zuber
Author-email: zuber.nicholas@gmail.com
License: MIT
Download-URL: https://github.com/user/reponame/archive/v_01.tar.gz
Keywords: chess,terminal,stockfish
Platform: UNKNOWN
